.gitignore
.readthedocs.yaml
CHANGES.md
CITATION.rst
CODE_OF_CONDUCT.md
CONTRIBUTING.md
Dockerfile
MANIFEST.in
README.rst
docker.py
environment.yml
pyproject.toml
requirements.txt
setup.cfg
setup.py
tox.ini
.github/workflows/ci_tests.yml
docs/Makefile
docs/api_reference.rst
docs/citing.rst
docs/conf.py
docs/correction_grids.ipynb
docs/fitting.ipynb
docs/fitting_workflow.ipynb
docs/index.rst
docs/installation.rst
docs/introduction.ipynb
docs/make.bat
docs/multi_object.ipynb
docs/petrosian.ipynb
docs/photometry.ipynb
docs/quick_start.ipynb
docs/release_procedure.rst
docs/_static/css/custom.css
docs/data/abell_2744_cd_galaxy_f105w.fits.gz
docs/data/abell_2744_dwarf_galaxy_f105w.fits.gz
docs/data/abell_2744_dwarf_galaxy_f105w_rms.fits.gz
docs/data/abell_2744_galaxy_f105w_photometry.ecsv
docs/data/abell_2744_group_of_galaxies_f105w.fits.gz
docs/data/abell_2744_spiral_galaxy_f105w.fits.gz
docs/data/example_rms.fits.gz
docs/data/example_sersic.fits.gz
docs/data/f105w_psf.fits.gz
docs/data/f105w_psf_corr.ecsv
docs/data/no_psf_corr.ecsv
docs/images/cd_galaxy_demo.png
docs/images/concentration_index_vs_epsilon.png
docs/images/concentration_index_vs_n.png
docs/images/doc_image_gen.ipynb
docs/images/doc_image_gen_old.ipynb
docs/images/f105w_concentration_index_vs_epsilon.png
docs/images/multi_fit.png
docs/images/petrofit_full_logo.png
docs/images/petrofit_full_logo.svg
docs/images/petrofit_logo.ico
docs/images/petrofit_logo.png
docs/images/petrofit_logo.svg
docs/images/petrofit_logo_no_bg.png
docs/images/petrofit_logo_no_bg.svg
docs/images/petrofit_logo_no_bg_color.png
docs/images/petrofit_logo_no_bg_color.svg
docs/images/sersic_cog.png
docs/images/sersic_index.png
docs/images/sersic_petrosian.png
docs/images/sersic_petrosian_eta.png
docs/images/sersic_radii.png
docs/temp/.keep
licenses/LICENSE.rst
licenses/README.rst
licenses/TEMPLATE_LICENCE.rst
petrofit/__init__.py
petrofit/_astropy_init.py
petrofit/conftest.py
petrofit/photometry.py
petrofit/segmentation.py
petrofit.egg-info/PKG-INFO
petrofit.egg-info/SOURCES.txt
petrofit.egg-info/dependency_links.txt
petrofit.egg-info/not-zip-safe
petrofit.egg-info/requires.txt
petrofit.egg-info/top_level.txt
