Metadata-Version: 2.1
Name: petrofit
Version: 0.5.1
Summary: Petrosian library
Home-page: https://github.com/PetroFit/petrofit
Author: The PetroFit Team
Author-email: 
License: BSD 3-Clause
Requires-Python: >=3.12
License-File: licenses/LICENSE.rst
Requires-Dist: Cython
Requires-Dist: numpy
Requires-Dist: matplotlib
Requires-Dist: astropy
Requires-Dist: scipy
Requires-Dist: pyyaml
Requires-Dist: scikit-learn
Requires-Dist: scikit-image
Requires-Dist: photutils
Provides-Extra: test
Requires-Dist: pytest-astropy; extra == "test"
Provides-Extra: docs
Requires-Dist: sphinx; extra == "docs"
Requires-Dist: sphinx-astropy; extra == "docs"
Requires-Dist: ipykernel; extra == "docs"
Requires-Dist: nbsphinx; extra == "docs"
Requires-Dist: sphinx_rtd_theme; extra == "docs"
Requires-Dist: ipywidgets; extra == "docs"
